CHANGES.txt
LICENSE
MANIFEST.in
README.rst
setup.py
docs/._make.bat
docs/Makefile
docs/make.bat
docs/build/html/._genindex.html
docs/build/html/._index.html
docs/build/html/._plots.py
docs/build/html/._plots_00.hires.png
docs/build/html/._plots_00.png
docs/build/html/._plots_01.hires.png
docs/build/html/._plots_01.png
docs/build/html/._plots_02.hires.png
docs/build/html/._plots_02.png
docs/build/html/._plots_03.hires.png
docs/build/html/._plots_03.png
docs/build/html/._plots_04.hires.png
docs/build/html/._plots_04.png
docs/build/html/._py-modindex.html
docs/build/html/._search.html
docs/build/html/genindex.html
docs/build/html/index.html
docs/build/html/plots.py
docs/build/html/plots_00.hires.png
docs/build/html/plots_00.png
docs/build/html/plots_01.hires.png
docs/build/html/plots_01.png
docs/build/html/plots_02.hires.png
docs/build/html/plots_02.png
docs/build/html/plots_03.hires.png
docs/build/html/plots_03.png
docs/build/html/plots_04.hires.png
docs/build/html/plots_04.png
docs/build/html/py-modindex.html
docs/build/html/search.html
docs/build/html/_images/._barplot_single.png
docs/build/html/_images/._exp_win.png
docs/build/html/_images/._gui.png
docs/build/html/_images/._gui1.png
docs/build/html/_images/._plots_00.png
docs/build/html/_images/._plots_01.png
docs/build/html/_images/._plots_02.png
docs/build/html/_images/._plots_03.png
docs/build/html/_images/._plots_04.png
docs/build/html/_images/._scheme.png
docs/build/html/_images/barplot_single.png
docs/build/html/_images/exp_win.png
docs/build/html/_images/gui.png
docs/build/html/_images/gui1.png
docs/build/html/_images/plots_00.png
docs/build/html/_images/plots_01.png
docs/build/html/_images/plots_02.png
docs/build/html/_images/plots_03.png
docs/build/html/_images/plots_04.png
docs/build/html/_images/scheme.png
docs/build/html/_modules/._index.html
docs/build/html/_modules/index.html
docs/build/html/_modules/psychopy_ext/._exp.html
docs/build/html/_modules/psychopy_ext/._fmri.html
psychopy_ext.egg-info/PKG-INFO
psychopy_ext.egg-info/SOURCES.txt
psychopy_ext.egg-info/dependency_links.txt
psychopy_ext.egg-info/top_level.txt
