Metadata-Version: 1.1
Name: psychopy-ext
Version: 0.6.0.4
Summary: A framework for a rapid reproducible experimental design, analysis and modeling of data in neuroscience and psychology.
Home-page: https://github.com/qbilius/psychopy_ext/
Author: Jonas Kubilius
Author-email: qbilius@gmail.com
License: GNU General Public License v3 or later
Keywords: psychology experiments plotting data visualization analysis fMRI simulations deep neural networks models hmax gaborjet hog phog reproducible research open science
Platform: UNKNOWN
Classifier: Development Status :: 4 - Beta
Classifier: Intended Audience :: Science/Research
Classifier: License :: OSI Approved :: GNU General Public License v3 or later (GPLv3+)
Classifier: Operating System :: OS Independent
Classifier: Programming Language :: Python :: 2.7
Classifier: Topic :: Scientific/Engineering
